project_explorer_mcp/__init__.py
project_explorer_mcp/config/__init__.py
project_explorer_mcp/config/logging.py
project_explorer_mcp/config/settings.py
project_explorer_mcp/main.py
project_explorer_mcp/tools/__init__.py
project_explorer_mcp/tools/dir_tree.py
project_explorer_mcp/tools/markdown_outline.py
project_explorer_mcp/tools/openapi_get_operation_details.py
project_explorer_mcp/tools/openapi_list_operations.py
project_explorer_mcp/tools/python_outline.py
project_explorer_mcp/utils/__init__.py
project_explorer_mcp/utils/formatters.py
project_explorer_mcp/utils/general.py
project_explorer_mcp/utils/openapi.py
project_explorer_mcp-0.1.0.dist-info/WHEEL
project_explorer_mcp-0.1.0.dist-info/entry_points.txt
project_explorer_mcp-0.1.0.dist-info/METADATA
project_explorer_mcp-0.1.0.dist-info/RECORD
