Metadata-Version: 2.3
Name: project-explorer-mcp
Version: 0.1.0
Summary: MCP server toolkit for analyzing the structure of a Python project
Keywords: mcp,model-context-protocol,code-analysis,python-analysis,ast,project-structure,code-outline,developer-tools,fastmcp
Author: l0kifs
Author-email: l0kifs <l0kifs91@gmail.com>
License: MIT
Classifier: Development Status :: 3 - Alpha
Classifier: Intended Audience :: Developers
Classifier: License :: OSI Approved :: MIT License
Classifier: Operating System :: OS Independent
Classifier: Operating System :: Microsoft :: Windows
Classifier: Operating System :: MacOS
Classifier: Operating System :: POSIX :: Linux
Classifier: Programming Language :: Python :: 3
Classifier: Programming Language :: Python :: 3.12
Classifier: Programming Language :: Python :: 3.13
Classifier: Topic :: Software Development :: Libraries :: Python Modules
Classifier: Topic :: Software Development :: Code Generators
Classifier: Topic :: Text Processing :: Markup :: Markdown
Classifier: Environment :: Plugins
Classifier: Natural Language :: English
Requires-Dist: fastmcp>=2.13.1
Requires-Dist: parso>=0.8.3
Requires-Dist: mistune>=3.1.4
Requires-Dist: loguru>=0.7.3
Requires-Dist: pydantic>=2.11.7
Requires-Dist: pydantic-settings>=2.10.1
Requires-Dist: pyyaml>=6.0.1
Maintainer: l0kifs
Maintainer-email: l0kifs <l0kifs91@gmail.com>
Requires-Python: >=3.12
Project-URL: Changelog, https://github.com/l0kifs/project-explorer-mcp/blob/main/CHANGELOG.md
Project-URL: Documentation, https://github.com/l0kifs/project-explorer-mcp/blob/main/README.md
Project-URL: Homepage, https://github.com/l0kifs/project-explorer-mcp
Project-URL: Issues, https://github.com/l0kifs/project-explorer-mcp/issues
Project-URL: Repository, https://github.com/l0kifs/project-explorer-mcp.git
